gitvars/__init__.py
gitvars/__main__.py
gitvars/config.txt
gitvars/printvars.py
gitvars/readvars.py
mf_gitvars-1.1.7.dist-info/METADATA
mf_gitvars-1.1.7.dist-info/WHEEL
mf_gitvars-1.1.7.dist-info/entry_points.txt
mf_gitvars-1.1.7.dist-info/top_level.txt
mf_gitvars-1.1.7.dist-info/RECORD
