Metadata-Version: 2.1
Name: mf-gitvars
Version: 1.1.7
Summary: A tool to parse CI/CD variables from Gitlab API
Home-page: UNKNOWN
Author: Adrian Mummey
Author-email: adrian@momentfeed.com
License: UNKNOWN
Platform: UNKNOWN
Classifier: Programming Language :: Python :: 3
Classifier: License :: OSI Approved :: MIT License
Classifier: Operating System :: OS Independent
Requires-Dist: python-gitlab
Requires-Dist: colorama
